finetuners/__init__.py
finetuners/abstract.py
finetuners/args.py
finetuners/dataset.py
finetuners/exceptions.py
finetuners/finetuner.py
finetuners/schemas.py
finetuners-0.0.1.dist-info/LICENSE
finetuners-0.0.1.dist-info/METADATA
finetuners-0.0.1.dist-info/WHEEL
finetuners-0.0.1.dist-info/top_level.txt
finetuners-0.0.1.dist-info/RECORD
