Metadata-Version: 2.1
Name: finetuners
Version: 0.0.1
Summary: Reduce cognitive load when finetuning transformers 🫠
Author-email: Kasper Junge <kasperjuunge@gmail.com>
Project-URL: Homepage, https://github.com/Dansk-Data-Science-Community/finetuners
Keywords: nlp,transformers
Classifier: Programming Language :: Python :: 3
Classifier: License :: OSI Approved :: MIT License
Classifier: Operating System :: OS Independent
Requires-Python: >=3.7
License-File: LICENSE
Requires-Dist: transformers
Requires-Dist: pandas
Requires-Dist: pandera
Requires-Dist: datasets
